pcu/__init__.py
pcu/arg_parser.py
pcu/color_utils.py
pcu/commands.py
pcu/compiler.py
pcu/config.py
pcu/defaults.py
pcu/environment.py
pcu/main.py
pcu/paths.py
pcu/problem.py
pcu/runner.py
pcu/testgen.py
pcu/yaml_util.py
pcu/static/default_settings.yaml
pcu/static/default_templates/c.c
pcu/static/default_templates/c_file.c
pcu/static/default_templates/cpp.cpp
pcu/static/default_templates/cpp_file.cpp
pcu/static/default_templates/java.java
pcu/static/default_templates/java_file.java
pcu/static/default_templates/python2.py
pcu/static/default_templates/python2_file.py
pcu/static/default_templates/python3.py
pcu/static/default_templates/python3_file.py
pcu-0.1.6.dist-info/licenses/LICENSE
pcu-0.1.6.dist-info/METADATA
pcu-0.1.6.dist-info/WHEEL
pcu-0.1.6.dist-info/entry_points.txt
pcu-0.1.6.dist-info/top_level.txt
pcu-0.1.6.dist-info/RECORD
