Metadata-Version: 2.4
Name: pcu
Version: 0.1.6
Summary: Comprehensive suite for competitive programming.
Author-email: Jerry Ma <jmnospam@mail.com>
License-Expression: BSD-3-Clause
Project-URL: Homepage, https://github.com/jma127/pcu
Requires-Python: >=3.10
License-File: LICENSE
Requires-Dist: colorama<1,>=0.4
Requires-Dist: filelock<4,>=3
Requires-Dist: inflection<1,>=0.5
Requires-Dist: pyyaml<7,>=6
Dynamic: license-file
